woaigpu/__init__.py
woaigpu/gpu.py
woaigpu-1.1.1.dist-info/METADATA
woaigpu-1.1.1.dist-info/WHEEL
woaigpu-1.1.1.dist-info/top_level.txt
woaigpu-1.1.1.dist-info/RECORD
