Metadata-Version: 2.1
Name: woaigpu
Version: 1.1.1
Summary: I love gpu, using it may lose friends.
Home-page: https://github.com/gaojunbin/woaigpu
Author: JunbinGao
Author-email: junbingao@hust.edu.cn
Maintainer: JunbinGao
Maintainer-email: junbingao@hust.edu.cn
License: MIT
Platform: all
Classifier: Operating System :: OS Independent
Classifier: Programming Language :: Python :: 3
Requires-Dist: emails
Requires-Dist: PyEmail
